KaraPy/Enums.py
KaraPy/First.py
KaraPy/KaraBrain.py
KaraPy/KaraWorld.py
KaraPy/XMLloader.py
KaraPy/__init__.py
KaraPy-0.5.7.dist-info/LICENSE
KaraPy-0.5.7.dist-info/METADATA
KaraPy-0.5.7.dist-info/WHEEL
KaraPy-0.5.7.dist-info/top_level.txt
KaraPy-0.5.7.dist-info/RECORD
