Metadata-Version: 2.1
Name: KaraPy
Version: 0.5.7
Summary: A Kara runtime for Python
Home-page: https://github.com/PixelboysTM/KaraPy
Author: Pixelboys_TM
Author-email: none@n.com
License: UNKNOWN
Platform: UNKNOWN
Classifier: Programming Language :: Python :: 3
Classifier: License :: OSI Approved :: MIT License
Classifier: Operating System :: OS Independent
Requires-Python: >=3.6
